[{
    "CGQQAA": [
        ["LjowFiFa6p0", "4k-acRDSkxE", "DCo2PgWSB_U", "neEzZHBFj9I", "cu6GkOUoAEo", "wxqGq6Bw5xM", "qGGdXKjwntU", "0PqBUDKYh9c", "4Vk-d1dX8eA", "gqBOmz5zNoc", "jxptIpCYAJA", "kij5nxP4hpo", "_bDStmosc9s", "QwfTWgOSPXU", "ek_Di-KEFhs", "UeGjQHwpzJA", "-uLe2VcUCJw", "wY-swlATQ2A", "6lDn_GNuCJA", "JmoIEG21sqg", "gEX787opZvE", "FmRhx3_22VY", "2IoVqnliVF4", "n1N8K9FT0RI", "biZPD9R30Sc", "PAupcE3tP3o", "l5aGG387ojE", "TfPeK9UEUY4", "RLSBf2ESMC4", "MyIJTSlTThU", "PmBWNVM1bIc", "6b-0dA8eBrw", "cT9-_-E7KX8", "J5-X7JT3o6o", "m0ygB_R_lHI", "7GlzW77TS2s", "L8O-MgxU6FY", "V-yfqGJjrz0", "772gJXo7gf4", "y-Jh440TQPY", "cuzY3rtrO28", "uktRwMO84bA", "JYUnGgUR_Lo", "kJ_gcTJKbXc", "DbcvpzeBSus", "jH2RtD7rb_w", "amt_FfyU7fE", "LzFc2ViT818", "jjxiTPk5Qwg", "fD_8qmCEjJ0"]
    ]
}, {
    "CJYBEAA": [
        ["_dRiU46Zkb0", "4EYkXgip4KQ", "6NbalVpgzQs", "7sLKr9kDsB4", "DOXBmIIZIXE", "dGJEkoupLa8", "povdepRgvlc", "H9YO-f6Df8g", "gzCkReCMLhk", "APShrOWeESc", "O2U5OlTOGCQ", "xrbSmNX3m6g", "4Rx0YrrF9Is", "8F_JM6yBo-M", "Ur0h9RetMWQ", "wKukXP6UFVo", "G0F0N6nK_5M", "R55NN4Be1Is", "8TwQ8JZuSyk", "oifGvwRdGI0", "BSaaCcOHXq4", "65FYaU-zv9s", "RLvD_kzd5X0", "sm_zyS-nOYo", "Mn_-ob9WRJ4", "YOftgh4EMbk", "FPf9OP981GE", "nsutV7Ib4Yc", "nWfAzgEmLho", "nl3YWJM_ojM", "qXzoZrdWijU", "NzlfiRWvz8w", "hFbpvOjsQRE", "tF0HwT_Xekw", "bxoAzy_r5VQ", "cCmuCZ-6KAI", "X5Eh_1qoqj0", "JFxOtxYJoz0", "0VtdyrwPkcY", "aIGjFwgrid0", "CmDWzKTXmj0", "DlLtZon5fHE", "_LbfrnfO-04", "z4z1KqR7Uuo", "VCbWDjS3r-U", "6DT_nYqP-aM", "X4ByXN4D6AY", "XOQTQuTIXUo", "DblwGfdmqQA", "604feyuwHXo"]
    ]
}, {
    "CMgBEAA": [
        ["604feyuwHXo", "z4z1KqR7Uuo", "VFHtpb34jFk", "QlwDhjOmg4I", "X4ByXN4D6AY", "oS7ZbTsx2Ok", "vQUiLcT8Y6c", "pGK82S-5PJs", "kojivtc0iew", "iECk6OGR-4A", "EtofW8d9ETU", "PsqFBT3vTCU", "koiqDDJtCQ8", "FUp1PBuokpo", "kpEMG_KAzHQ", "rD2yKF-G_l0", "ryO9eABrqaU", "kY1boEjKO4M", "z4ILrNdGlfA", "hfxYwX6dlz8", "Dzed-wt4XkI", "4mqezQaBtcc", "EGqpZ3-MpVc", "nWfAzgEmLho", "CJFvw2fMomM", "JQYOCoj3XJE", "BONgyRhJOuU", "QAt6PePbdZk", "jQ-TOK2FiI4", "-SGstL9zkms", "hY9fJo7G4Cg", "noiLnVzM-7Q", "ExAEDQ26HTE", "nYS0R4c3qCA", "2Wj-Xi6TfIg", "e-_CPof9zbM", "CmDWzKTXmj0", "O3xIGtDU3d0", "Dy4SXRh-5bI", "d8P01xih9Ko", "EjctWA0PIDg", "5QT954iWSU0", "WSUU_DaudR4", "p7QPq2Do4dI", "nXuP661DSCo", "7S09yH4umJg", "TDhmNgsgf8s", "Z12Q86P2yQ0", "cBMHJVDSt0E", "qDuthCSiLao"]
    ]
}, {
    "CPoBEAA": [
        ["5L0VEZGkXOE", "oBveAitNdlE", "8-Gl2uhXFyQ", "_0mBGA7IWXI", "NTAmXpP2Y2M", "zQrQ13WGeMc", "_qGAxZscYSE", "PrfEzh8tEtA", "FWDZi6JyWmk", "KPdlPmQbt3U", "6YPNUITrFa4", "p3qmASseZRI", "ODQoZYZmxoA", "XjL4CaTR3dQ", "csA4KQRis5A", "fcW7txat7qQ", "Z_YqFkX3d6g", "Vg6TwhhcuGA", "UCBtS2W7_Ro", "UTr-iy3LVok", "VjQCajR1oTQ", "WYWlzCRAeSo", "6GXLumQehGg", "wfaWTan8jRc", "1MyK_ATJH_0", "9L77BLA2qSw", "X6J1fD4u2t8", "KwmqGjcZp3o", "tOBTgz0JuiI", "JDKl9jzPQxo", "migmxXB47-0", "wV1Jh6ly7wc", "zDGa3YLWYuA", "qOvlZcgOYQs", "ykrhBHuuR9U", "aTsMgVZw9QM", "U1HDiwpVY18", "_BTzHgblHUU", "oZTz5OOmiIA", "llvj2GuCB7g", "LNhJbI3euwA", "80Mn7AZKXkY", "DqaB11ITaBo", "SO0g492-_Zs", "_AS8_uK_Svo", "PPzsy5W0uQg", "qzyT5mU9BHM", "4yZtPYIX5BI", "zK8Nrnlkdtk", "NcoZrZZwCjs"]
    ]
}, {
    "CKwCEAA": [
        ["SO0g492-_Zs", "Xy6PDa0G5iI", "NcoZrZZwCjs", "p-5Bte4qUmU", "qzyT5mU9BHM", "4yZtPYIX5BI", "0rwF00Vjiuo", "zK8Nrnlkdtk", "TgmBlEI4Ib0", "S8AvWSdGlVQ", "DMbOO7Xsjug", "K-p0S54pzFY", "678BhpEonro", "ykVgEMf0shw", "LZeVRMwrJh4", "8UQ_0HXqgyk", "mGdIq4RGM0I", "kQS6B6x7ubw", "FqQ2EVzL948", "AzzC74hCvqk", "64o0nU9phyk", "oqraCPFK9eU", "pmqOz-gQx5w", "aWQn5ZX62G0", "KnsAT1Ri9Yw", "sAThAkaqKIk", "ax9H2Jr9VcU", "Mi2Rwmw5Sus", "MVXrIkMOuK4", "CRxHnoVQnOE", "M3AUtcr9NP4", "3AbmoQ6wif8", "MwYGf87t00Y", "bubPSdbg2lA", "4hxLQC_8tRs", "7zZKa-vQ9O0", "fghpmPo8uOk", "6ZMQvkOyQB4", "lOpGnwYP8PY", "0HerqsNTZLU", "iqLrO14Sv3I", "yML-wyP18M4", "NP677WTyK6k", "cPtZou2gl_c", "5-nBfRY3TtA", "d0pWVz-yUac", "DkmY8hC7tWQ", "XCRuvSUk3-Q", "C2PPak6Wo4s", "LdNf5KxtbE0"]
    ]
}, {
    "CN4CEAA": [
        ["bFa81QVYObI", "HCF87eTnVDo", "3c6MqOB4n9o", "HQXgbSUQ0Yo", "Poid-4mfNvA", "8DeJMkICseA", "zDq1f31Wbo0", "H0asFWn08wc", "rCBAqP42NSA", "ycQ3-Jgqd1Q", "6lEmkmzzcqc", "Ph9qTllhPjo", "izt3eDEqt4o", "YaL0mgpI7K4", "Zc_0IUftEzU", "Q9Q4tSjvfbw", "7ULoKBh-TBY", "hVL44oxUdbc", "d59GzcG37Jw", "SYMD5uUibrk", "YyyvhkO428M", "HZQoD0eeueQ", "cm_0dkNpfdw", "IfARbHEq2NI", "Y7cZZL2MzYo", "AIvwVCoVUes", "xkZLpZX7Tm0", "HpsfA7PwyZk", "uh84qe8KUNs", "cUfYpezSWVc", "tIyxrPJylBA", "v8i3PoMXGUc", "DGyRD9HnXVs", "1o_peex2lV0", "3m3764mZ_u0", "Y-IlMeCCtIg", "7YM2EKc0Tk4", "jzu7r6ii7cQ", "s2wO29K7al0", "53wv2B4_X2s", "VTyJgoyKwLk", "g0NVSC6x9E4", "KLvdk4YqSMc", "sEL4ICu30zs", "LOK5NPmDIxU", "yhv1yuRwdC8", "hjpdGI71j3w", "eV2dtE68HWY", "spdwRUZtwjQ", "VrCTYmw6W60"]
    ]
}, {
    "CJADEAA": [
        ["8e2_qiPOFRc", "hjpdGI71j3w", "LXFSfTEmFj8", "spdwRUZtwjQ", "I5JD6bwSv2I", "FaHhkSW27B0", "wntibFg1ZRI", "gN78d_lSVkY", "RQSjQqI_ry8", "edeMyJA0txU", "fsEl03Xkp1k", "JqO98Lfludg", "Mw88lGxk3W4", "pFRvKUmj8os", "GsvKQJn9OZE", "pH54tVgLp34", "ZWmL3Md2eCA", "R4Y5wGJJ4oU", "gho41Y0Amuw", "qx1B54gMX_E", "ypMKE05EyxQ", "0Cwsvm6Bogo", "kxp_Tarob80", "kO-p40GHg6o", "Z1ze7GcDwus", "3KXnIxvplS8", "Ocw4NMyjdY8", "xoga5lN6TN8", "1ht_EYVQfwQ", "RjHErq2CCzk", "KkI-2bVyHCQ", "JTjg_xkPmW8", "4jfi1cRtHXY", "cPrA9BGxdIo", "68lejFBHQc0", "keyMG5dqI9g", "xmsQml6-x88", "aNFPcK2vLR8", "FkjKxDotjf8", "KUfg6we36mk", "G1DxVCgpI34", "pW4uw2K-I6Y", "t9bJ3I1Fm6g", "Siph7B5y6LY", "udZz2_E4SXw", "GT8zs_V3QDk", "qKzDh5cy0y4", "uQyKi_7ke6Q", "HAahMnY0JMM", "0uTs884yfeo"]
    ]
}, {
    "CMIDEAA": [
        ["NtEi-Y2veWc", "byUWHvJ1BYc", "pzMgAw_h2CI", "SOnCBbqwl3o", "V7tETyRvgn8", "d9IMVdNiTQM", "XDVYYvw9wWk", "GNtjgBDgF7o", "GxT5n5LQeAA", "xiCkFuxn6L0", "LeFM2q3J76Y", "BqczvHr-FzA", "23q6eNufxZQ", "tMVS6TZ2qcI", "ALejpZWfPLQ", "p_O_q_TFgxg", "YUIkRjmk0A0", "a7A39P2vfXU", "T29BTs4zWds", "HyaSMDJoqL0", "yN0Rfj1YfA4", "6BU3hmm_6S8", "eIl0QbO7GNM", "Qb1xG20KdOk", "wftAPblxQjg", "8G36Uoq5Uyo", "kixXqcRZrds", "daCjgtsq2fA", "3ypJl4AqsXs", "dVQ-K5VDI7c", "FmFanN4WRu4", "wLfx6zd4fec", "LNVG1r4o7B4", "RnYmhRswNR8", "GvkB2lwTfGs", "L3hIA9Q2k6U", "vxITzoTW6vw", "jcgZAJP68lU", "6VWwRuahynw", "OjHaA4VAfhM", "I39xZHYHB5A", "aYbeYi9GhHo", "-MisE7Y6dKo", "8UbiX91aHA4", "onGqqjH72PY", "LrkTuwOyado", "9Rvncx0TaSc", "vZz3YDBSuLA", "FQNwoXrruqc", "kAke_5qkGPI"]
    ]
}, {
    "CPQDEAA": [
        ["kAke_5qkGPI", "jcgZAJP68lU", "I39xZHYHB5A", "vZz3YDBSuLA", "onGqqjH72PY", "0buZoTPz27M", "QHK7P2HAfsA", "sKVWJNa3uqE", "FdDtAwnLThI", "2snWMJHjCZY", "LrkTuwOyado", "CJOBfyhMsek", "7cbilgf9XAU", "zYCsBas5vK8", "Mu0CZ1MHFKY", "Cwx7JaPGkag", "6BbYcxqPGuE", "x8v051O3iRM", "zlXi6PmHRMw", "Fk8RNsdo43Q", "a7A39P2vfXU", "5rRKN1a8wII", "aEQVvNIolrs", "nttNrZHTSww", "6095Ryc3XrM", "lVvMP0nclVQ", "f33HSkCRd48", "w4qgDG7D6cM", "wLXDrfgnBfI", "7nVlc7mXilk", "O4uqWfRP9uU", "uD609iE7qMM", "tey_14zRjVQ", "9LsHp-tgx8w", "xqkOXUcmlTw", "Az3wqP7MiiU", "vKgPQ03tsv0", "Sk7i02FC70U", "P5ow6uff6hY", "6RdSSMMZpvY", "337kBtX7Wpo", "jnWVc_nP6qI", "NO7BbsIL_j8", "xB9BBU4r8i8", "_ijuuX2Q1dc", "lSjnr2O7qdM", "gJu2AiU4k94", "dhOUUBmC2ss", "krgQvnhfyuU", "6Z7jQC-XUfg"]
    ]
}, {
    "CKYEEAA": [
        ["krgQvnhfyuU", "sP8MSZl4YQs", "zcAvu4ohKwg", "a9h1Bju4Izo", "dVUYNwUKINM", "bGq2U8sgrlg", "rwP_yzchDZc", "Om40dT9n9rY", "_ijuuX2Q1dc", "8R8uQy-W9kk", "FQcLcIquJ7k", "vW-jXjWS690", "Ep-Ct-8J7O0", "rRiMm4dQuck", "KSkDqbL_pVE", "zVz5if0LOAg", "Io30I1IL5Cg", "PKb4NuFkdwM", "Qkh8fWnSXnU", "pVvClcPpjNE", "ucyQONcNqF4", "V9wM6pvs71g", "jtOFWOeAw_0", "SwNLIex40ak", "9ETSjlXvx6g", "epg50CNdQ-o", "5kI1aodilxs", "5hC2tWFpvjs", "YhnvsBRJYhw", "sycuSTYxInI", "Wyv5_MmR4Mw", "exXnGI010CA", "YMHP3wWrK8c", "FGYNQk7NK0k", "Xc41ABh6flk", "zHDcyns15w4", "1BCLlf-_p4U", "_7EY2-s7-pU", "wZWRg_paJ3U", "1q8UgA4MAm4", "-aWU_yWmujQ", "o1hC6hxRqBU", "kOQd8yc84NU", "Rz0XtM58QFk", "Pk16aLRG2pk", "gE_BxKsf5z4", "hIY8JptuY4k", "RufEEHOZtEI", "Q7v-NguZgLE", "5tuPorzWI0k"]
    ]
}]